 [
    {
      "id": 1416,
      "name": "javascript",
      "type": "languages",
      "match": 41676,
      "color": "#F7DC6F",
      "avatar": "https://cdn-icons-png.flaticon.com/512/5968/5968292.png",
      "existing": true
    },
    {
      "id": 1417,
      "name": "react native",
      "type": "frameworks",
      "match": 41677,
      "color": "#61DAFB",
      "avatar": "https://encrypted-tbn0.gstatic.com/images?q=tbn:ANd9GcSlGmKtrnxElpqw3AExKXPWWBulcwjlvDJa1Q&s",
      "existing": true
    },
    {
      "id": 1418,
      "name": "leonardo da vinci",
      "type": "art",
      "match": 41678,
      "color": "#F5DEB3",
      "avatar": "https://encrypted-tbn3.gstatic.com/images?q=tbn:ANd9GcTZqMi_i8qdx5bhvamUW3I7zLjddOaPT3PpDf2ss1UY48FRdx4Fl1ujt5zVcjD34YFH7QUAAzb8AduhxPEhzjbxgg",
      "existing": true
    },
    {
      "id": 1419,
      "name": "absolute cinema",
      "type": "movies",
      "match": 41679,
      "color": "#F5DEB3",
      "avatar": "https://upload.wikimedia.org/wikipedia/commons/thumb/6/69/IMDB_Logo_2016.svg/1200px-IMDB_Logo_2016.svg.png",
      "existing": true
    },
    {
      "id": 1420,
      "name": "python",
      "type": "languages",
      "match": 41680,
      "color": "#306998",
      "avatar": "https://upload.wikimedia.org/wikipedia/commons/thumb/c/c3/Python-logo-notext.svg/1200px-Python-logo-notext.svg.png",
      "existing": true
    },
    {
      "id": 1421,
      "name": "vue.js",
      "type": "frameworks",
      "match": 41681,
      "color": "#42b883",
      "avatar": "https://static-00.iconduck.com/assets.00/vue-icon-2048x2048-ttu9fp8c.png",
      "existing": true
    },
    {
      "id": 1422,
      "name": "salvador dali",
      "type": "art",
      "match": 41682,
      "color": "#FFD700",
      "avatar": "https://encrypted-tbn0.gstatic.com/images?q=tbn:ANd9GcTbpAS_QvwfzlDIVpnWfKDKZVIGPJ65gj6EY9ca7M84eZ6jOPN48ZXO9fNxIW9nivv088Q&usqp=CAU",
      "existing": true
    }
  ]